google_music_utils/__about__.py
google_music_utils/__init__.py
google_music_utils/compare.py
google_music_utils/constants.py
google_music_utils/filter.py
google_music_utils/metadata.py
google_music_utils/misc.py
google_music_utils/utils.py
google_music_utils-2.5.0.dist-info/LICENSE
google_music_utils-2.5.0.dist-info/WHEEL
google_music_utils-2.5.0.dist-info/METADATA
google_music_utils-2.5.0.dist-info/RECORD
