Metadata-Version: 2.1
Name: google-music-utils
Version: 2.5.0
Summary: A set of utility functionality for google-music and related projects.
Home-page: https://github.com/thebigmunch/google-music-utils
License: MIT
Author: thebigmunch
Author-email: mail@thebigmunch.me
Requires-Python: >=3.6,<4.0
Classifier: License :: OSI Approved :: MIT License
Classifier: Programming Language :: Python :: 3
Classifier: Programming Language :: Python :: 3.6
Classifier: Programming Language :: Python :: 3.7
Classifier: Programming Language :: Python :: 3.8
Provides-Extra: dev
Provides-Extra: doc
Provides-Extra: lint
Provides-Extra: test
Requires-Dist: audio-metadata (>=0.9)
Requires-Dist: coverage[toml] (>=5.0,<6.0); extra == "dev" or extra == "test"
Requires-Dist: flake8 (>=3.5,<4.0); extra == "dev" or extra == "lint"
Requires-Dist: flake8-builtins (>=1.0,<2.0); extra == "dev" or extra == "lint"
Requires-Dist: flake8-comprehensions (>=2.0,<=4.0); extra == "dev" or extra == "lint"
Requires-Dist: flake8-import-order (>=0.18,<0.19); extra == "dev" or extra == "lint"
Requires-Dist: flake8-import-order-tbm (>=1.0,<2.0); extra == "dev" or extra == "lint"
Requires-Dist: more-itertools (>=4.0,<9.0)
Requires-Dist: multidict (>=4.0,<5.0)
Requires-Dist: nox (>=2019,<2020); extra == "dev" or extra == "test"
Requires-Dist: pytest (>=4.0,<6.0); extra == "dev" or extra == "test"
Requires-Dist: sphinx (>=2.0,<3.0); extra == "dev" or extra == "doc"
Requires-Dist: sphinx-material (<1.0.0); extra == "dev" or extra == "doc"
Requires-Dist: wrapt (>=1.0,<2.0)
Project-URL: Repository, https://github.com/thebigmunch/google-music-utils
